column_classifier/__init__.py
column_classifier/column_classifier.py
tests/__init__.py
tests/test_classifier.py
column_classifier-0.1.7.dist-info/LICENSE
column_classifier-0.1.7.dist-info/METADATA
column_classifier-0.1.7.dist-info/WHEEL
column_classifier-0.1.7.dist-info/top_level.txt
column_classifier-0.1.7.dist-info/RECORD
